gabriel/__init__.py
gabriel/archangel.py
gabriel/elo_ratings_code.py
gabriel/foundational_functions.py
gabriel/openai_api_calls.py
gabriel/teleprompter.py
gabriel/Prompts/__init__.py
gabriel/Prompts/attribute_description_prompt.j2
gabriel/Prompts/classification_prompt.j2
gabriel/Prompts/clean_json_prompt.j2
gabriel/Prompts/elo_prompt.j2
gabriel/Prompts/generic_classification_prompt.j2
gabriel/Prompts/identify_categories_prompt.j2
gabriel/Prompts/list_generation_prompt.j2
gabriel/Prompts/ratings_prompt.j2
gabriel/Prompts/ratings_prompt_full.j2
gabriel/Prompts/type_of_tech_format.j2
GABRIEL_ratings-2.0.3.dist-info/LICENSE
GABRIEL_ratings-2.0.3.dist-info/METADATA
GABRIEL_ratings-2.0.3.dist-info/WHEEL
GABRIEL_ratings-2.0.3.dist-info/top_level.txt
GABRIEL_ratings-2.0.3.dist-info/RECORD
