Metadata-Version: 2.1
Name: GABRIEL-ratings
Version: 2.0.3
Summary: THE GABRIEL library for numerical analysis of texts in the social sciences.
Home-page: https://github.com/elliottmokski/GABRIEL-distribution
Author: Hemanth Asirvatham and Elliott Mokski
Author-email: elliottpmokski@gmail.com
Classifier: Programming Language :: Python :: 3
Classifier: License :: OSI Approved :: GNU General Public License v3 (GPLv3)
Requires-Python: >=3.6
License-File: LICENSE
Requires-Dist: numpy >=1.18.0
Requires-Dist: pandas >=1.0.0
Requires-Dist: openai >=1.0.0
Requires-Dist: Jinja2 >=2.11.0
Requires-Dist: tqdm >=4.42.0
Requires-Dist: tiktoken >=0.2.0
Requires-Dist: aiohttp >=3.7.0
Requires-Dist: aiolimiter >=1.0.0
